{"aarti":{"title":"आरत्या","list":{"sukhakarta-dukhaharta":{"title":"सुखकर्ता दुखःहर्ता","audioUrl":"http://adityamhamunkar.com/bappamusic/aarti/1-sukhakarta-dukhaharta.mp3","lyrics":"\nसुखकर्ता दुखःहर्ता वार्ता विघ्नाची।\nनुरवी पुरवी प्रेम कृपा जयाची। \nसर्वांगी सुंदर उटी शेंदुराची। \nकंठी झळके माळ मुक्ताफळांची।।१॥ \n\nजय देव जय देव जय मंगलमुर्ती ॥ \nदर्शनमात्रे मन कामनापुर्ति॥ध्रु॥ \n\nरात्नखचीत फरा तुज गौरिकुमरा। \nचंदनाची उटी कुंकुम केशरा । \nहिरेजडीत मुगुट शोभतो बरा। \nरुणझुणती नुपुरे\nचरणी घागरिया ॥ जय देव॥२॥  \n\nलम्बोदर पितांबर फणिवरबंधना । \nसरळ सोंड वक्र तुंड त्रिनयना।  \nदास रामाचा वाट पाहे सदना । \nसंकटी पावावे निर्वाणी रक्षावे \nसुरवर वंदना ॥जय देव॥३॥      \n      \n      "},"lavthavti-vikrala":{"title":"लवथवती विक्राळा","audioUrl":"http://adityamhamunkar.com/bappamusic/aarti/2-lavthavti-vikrala.mp3","lyrics":"\nलवथवती विक्राळा ब्रम्हांडी माळा\nविषे कंठ काळा त्रिनेत्री ज्वाळा  ।\nलावण्यसुंदर मस्तकी बाळा\nतेथुनिया जळ निर्मळ वाहे झुळझुळा\nजयदेव जयदेव जय श्रीशंकरा\nआरती ओवाळू तुज कर्पुरगौरा ॥  १ ॥\n\nकर्पुरगौरा भोळा  नयनी विशाळा\nअर्धांगी पार्वती सुमनांच्या माळा ।\nविभूतीचे उधळण शितिकठ निळा\nऐसा शंकर शोभे उन्म्हा वेल्हाळा  ॥ २ ॥\nजयदेव…\n\nदैवी दैत्यी सागर मंथन पै  केले\nत्यामाजी अवचित हळाहळ  उठिले ।\nते त्वा असुरपणे प्राशन  केले\nनिळकंठ नाम प्रसिद्ध झाले  ॥॥ ३ ॥\nजयदेव…\n\nव्याघ्रांबर फणिवरधर सुंदर मदनारी\nपंचानन मनमोहन मुनिजन सुखकारी  ।\nशतकोटीचे बीज वाचे उच्चारी\nरघुकुळटिळक रामदासा अंतरी  ॥ ४ ॥\nजयदेव...\n    "},"durge-durghat":{"title":"दुर्गे दुर्घट भारी","audioUrl":"http://adityamhamunkar.com/bappamusic/aarti/3-durge-durgahat.mp3","lyrics":"\nदुर्गे दुर्घट भारी तुजवीण संसारी\nअनाथ नाथे अंबे करुणा  विस्तारी ।\nवारी वारी जन्म मरणाते वारी\nहारी पडलो आता संकट निवारी ॥\nजय देवी जय देवी महिषासुरमर्दिनी\nसुरवर ईश्वर वरदे तारक संजीवनी ॥\n\nत्रिभुवन भुवनी पाहता तुज ऐसी नाही\nचारी श्रमले परंतु न बोलवे काही । \nसाही विवाद करिता पडले प्रवाही\nते तू भक्तालागी पावसी लवलाही ॥\nजयदेव ...\n\nप्रसन्न वदने प्रसन्न होसी  निजदासा\nक्लेशा पासुनी सोडवी तोडी भवपाशा ।\nअंबे  तुज वाचून कोण पुरवील आशा\nनरहरी तल्लीन झाला पद्पंकजलेषा ॥\nजयदेव ... \n    "}}},"gajar":{"title":"गजर","list":{"ashtavinayak":{"title":"अष्टविनायक","lyrics":""}}},"shlok":{"title":"श्लोक","list":{"sada-sarvada":{"title":"सदा सर्वदा","lyrics":""},"morya-morya":{"title":"मोरया मोरया","lyrics":""}}},"mangalashtak":{"title":"मंगलाष्टके","list":{"swasti-shree":{"title":"स्वस्ति श्री"}}}}